pybabblesdk/__init__.py
pybabblesdk/blockchain/__init__.py
pybabblesdk/blockchain/block.py
pybabblesdk/rpc/__init__.py
pybabblesdk/rpc/jsonrpctcpclient.py
pybabblesdk/rpc/jsonrpctcpserver.py
pybabblesdk-0.2.2.dist-info/METADATA
pybabblesdk-0.2.2.dist-info/RECORD
pybabblesdk-0.2.2.dist-info/WHEEL
pybabblesdk-0.2.2.dist-info/top_level.txt
