Metadata-Version: 2.1
Name: pybabblesdk
Version: 0.2.2
Summary: An SDK for developing Babble clients in python.
Home-page: http://github.com/babbleio/pybabblesdk
Author: Kevin Jones
Author-email: kevin@babble.io
License: UNKNOWN
Keywords: babble,babblesdk,sdk,pybabble,python babble,babble python,pybabblesdk
Platform: UNKNOWN
Requires-Dist: six
Requires-Dist: requests
